setup.py
client/__init__.py
client/add_contact.py
client/database.py
client/del_contact.py
client/main_window.py
client/main_window_conv.py
client/start_dialog.py
client/transport.py
common/__init__.py
common/decos.py
common/descryptors.py
common/errors.py
common/metaclasses.py
common/utils.py
common/variables.py
logs/__init__.py
logs/config_client_log.py
logs/config_server_log.py
mess_client_dima_pro.egg-info/PKG-INFO
mess_client_dima_pro.egg-info/SOURCES.txt
mess_client_dima_pro.egg-info/dependency_links.txt
mess_client_dima_pro.egg-info/top_level.txt
unit_tests/__init__.py