Metadata-Version: 2.1
Name: mess-client-dima-pro
Version: 0.1
Summary: Client packet
Author: Dima Protasevich
Author-email: dima_protasevich92@mail.ru
